hvps/__init__.py
hvps/__main__.py
hvps/version.py
hvps/commands/__init__.py
hvps/commands/caen/__init__.py
hvps/commands/caen/channel.py
hvps/commands/caen/module.py
hvps/commands/iseg/__init__.py
hvps/commands/iseg/channel.py
hvps/commands/iseg/module.py
hvps/devices/__init__.py
hvps/devices/channel.py
hvps/devices/hvps.py
hvps/devices/module.py
hvps/devices/caen/__init__.py
hvps/devices/caen/caen.py
hvps/devices/caen/channel.py
hvps/devices/caen/module.py
hvps/devices/iseg/__init__.py
hvps/devices/iseg/channel.py
hvps/devices/iseg/iseg.py
hvps/devices/iseg/module.py
hvps/devices/iseg/output.py
hvps/devices/iseg/script.py
hvps/utils/__init__.py
hvps/utils/utils.py
hvps-0.1.0.dist-info/METADATA
hvps-0.1.0.dist-info/WHEEL
hvps-0.1.0.dist-info/licenses/LICENSE
hvps-0.1.0.dist-info/RECORD
