Metadata-Version: 2.1
Name: hvps
Version: 0.1.0
Summary: An unofficial Python package 🐍📦 to interface with CAEN high voltage power supplies
Project-URL: Download, https://github.com/lobis/hvps/releases
Project-URL: Homepage, https://github.com/lobis/hvps
Project-URL: Bug Tracker, https://github.com/lobis/hvps/issues
Author-email: Luis Antonio Obis Aparicio <luis.antonio.obis@gmail.com>
License-File: LICENSE
Classifier: Operating System :: OS Independent
Classifier: Programming Language :: Python :: 3
Requires-Python: >=3.8
Requires-Dist: pyserial
Provides-Extra: dev
Requires-Dist: pre-commit; extra == 'dev'
Requires-Dist: pytest; extra == 'dev'
Provides-Extra: test
Requires-Dist: pytest; extra == 'test'
